porespy/__init__.py
porespy/beta/__init__.py
porespy/beta/_dns_tools.py
porespy/beta/_fiber_gen.py
porespy/beta/_generators.py
porespy/beta/_poly_cylinders.py
porespy/beta/_sphere_insertions.py
porespy/beta/_tortuosity_bt_funcs.py
porespy/dns/__init__.py
porespy/dns/_funcs.py
porespy/filters/__init__.py
porespy/filters/_displacement.py
porespy/filters/_fftmorphology.py
porespy/filters/_fill_and_find.py
porespy/filters/_funcs.py
porespy/filters/_lt_methods.py
porespy/filters/_morphology.py
porespy/filters/_nlmeans.py
porespy/filters/_size_seq_satn.py
porespy/filters/_snows.py
porespy/filters/_transforms.py
porespy/generators/__init__.py
porespy/generators/_fractals.py
porespy/generators/_imgen.py
porespy/generators/_micromodels.py
porespy/generators/_noise.py
porespy/generators/_pseudo_packings.py
porespy/generators/_spheres_from_coords.py
porespy/io/__init__.py
porespy/io/_funcs.py
porespy/io/_unzipper.py
porespy/metrics/__init__.py
porespy/metrics/_funcs.py
porespy/metrics/_meshtools.py
porespy/metrics/_regionprops.py
porespy/metrics/_rev.py
porespy/networks/__init__.py
porespy/networks/_funcs.py
porespy/networks/_getnet_orig.py
porespy/networks/_getnet_para.py
porespy/networks/_magnet.py
porespy/networks/_size_factors.py
porespy/networks/_snow2.py
porespy/networks/_utils.py
porespy/simulations/__init__.py
porespy/simulations/_dns.py
porespy/simulations/_drainage.py
porespy/simulations/_examples.py
porespy/simulations/_hg_porosimetry.py
porespy/simulations/_ibip_gpu.py
porespy/simulations/_imbibition.py
porespy/simulations/_injection.py
porespy/simulations/_tests.py
porespy/tools/__init__.py
porespy/tools/_funcs.py
porespy/tools/_marching_cubes.py
porespy/tools/_marching_squares.py
porespy/tools/_morphology.py
porespy/tools/_sphere_insertions.py
porespy/tools/_utils.py
porespy/tools/marching_cubes_templates.dat
porespy/visualization/__init__.py
porespy/visualization/_funcs.py
porespy/visualization/_plots.py
porespy/visualization/_views.py
porespy-3.0.3.dist-info/METADATA
porespy-3.0.3.dist-info/WHEEL
porespy-3.0.3.dist-info/licenses/LICENSE
porespy-3.0.3.dist-info/RECORD
