Metadata-Version: 2.4
Name: porespy
Version: 3.0.3
Summary: A set of tools for analyzing 3D images of porous materials
Project-URL: Homepage, https://porespy.org
Project-URL: Repository, https://github.com/PMEAL/porespy
Project-URL: Bug Tracker, https://github.com/PMEAL/porespy/issues
Project-URL: Documentation, https://porespy.org
Author-email: PoreSpy Team <jgostick@gmail.com>
Maintainer-email: Jeff Gostick <jgostick@gmail.com>, Amin Sadeghi <amin.sadeghi@live.com>
License-Expression: MIT
License-File: LICENSE
Keywords: direct numerical simulation,image analysis,porous materials,voxel images
Classifier: Development Status :: 5 - Production/Stable
Classifier: Operating System :: OS Independent
Classifier: Programming Language :: Python
Classifier: Programming Language :: Python :: 3
Classifier: Topic :: Scientific/Engineering
Classifier: Topic :: Scientific/Engineering :: Physics
Requires-Python: <3.14,>=3.11
Requires-Dist: dask
Requires-Dist: deprecated
Requires-Dist: edt
Requires-Dist: matplotlib
Requires-Dist: matplotlib-inline>=0.1.7
Requires-Dist: numba
Requires-Dist: numpy
Requires-Dist: pandas
Requires-Dist: psutil
Requires-Dist: rich
Requires-Dist: scikit-image>=0.25.0
Requires-Dist: scipy
Requires-Dist: setuptools
Requires-Dist: tomli>=2.2.1
Requires-Dist: tqdm
Provides-Extra: extras
Requires-Dist: imageio; extra == 'extras'
Requires-Dist: nanomesh; extra == 'extras'
Requires-Dist: numpy-stl; extra == 'extras'
Requires-Dist: openpnm; extra == 'extras'
Requires-Dist: pandoc>=2.4; extra == 'extras'
Requires-Dist: pyevtk; extra == 'extras'
Requires-Dist: pywavelets; extra == 'extras'
Requires-Dist: scikit-learn; extra == 'extras'
Requires-Dist: trimesh; extra == 'extras'
